AIOdriver/functions.py
AIOdriver-0.1.4.dist-info/LICENSE
AIOdriver-0.1.4.dist-info/METADATA
AIOdriver-0.1.4.dist-info/WHEEL
AIOdriver-0.1.4.dist-info/top_level.txt
AIOdriver-0.1.4.dist-info/RECORD
