Metadata-Version: 2.1
Name: AIOdriver
Version: 0.1.4
Summary: All in one driver
Home-page: https://github.com/abhishake99/AIOdriver
Author: Abhishek Ramawat
Author-email: ramawatabhishek22@gmail.com
License: MIT
Project-URL: Bug Tracker, https://github.com/mike-huls/toolbox/issues
License-File: LICENSE
